censaurus/__init__.py
censaurus/api.py
censaurus/census_accessors.py
censaurus/constants.py
censaurus/dataset.py
censaurus/geography.py
censaurus/graph_utils.py
censaurus/internals.py
censaurus/recode.py
censaurus/regroup.py
censaurus/rename.py
censaurus/tiger.py
censaurus/variable.py
censaurus/_data/state_ids.csv
censaurus-0.1.1.5.dist-info/LICENSE.txt
censaurus-0.1.1.5.dist-info/METADATA
censaurus-0.1.1.5.dist-info/WHEEL
censaurus-0.1.1.5.dist-info/top_level.txt
censaurus-0.1.1.5.dist-info/RECORD
