Metadata-Version: 2.1
Name: censaurus
Version: 0.1.1.5
Summary: A comprehensive, feature-rich, and user-oriented Python package that wraps the U.S. Census Bureau's Data and Geographic APIs
Author: Ethan Singer
Author-email: Ethan Singer <singerep@bu.edu>
Project-URL: Homepage, https://github.com/singerep/censaurus
Project-URL: Documentation, https://censaurus.readthedocs.io/en/latest/
Project-URL: Issues, https://github.com/singerep/censaurus/issues
Classifier: Programming Language :: Python :: 3
Classifier: License :: OSI Approved :: BSD License
Classifier: Operating System :: OS Independent
Requires-Python: >=3.7
License-File: LICENSE.txt
Requires-Dist: Fiona
Requires-Dist: geopandas
Requires-Dist: httpx
Requires-Dist: importlib-resources
Requires-Dist: matplotlib
Requires-Dist: numpy
Requires-Dist: pandas
Requires-Dist: python-Levenshtein
Requires-Dist: pyvis
Requires-Dist: scipy
Requires-Dist: setuptools
Requires-Dist: Shapely
Requires-Dist: thefuzz
